hns_tr069_sdk/__init__.py
hns_tr069_sdk/axiros/__init__.py
hns_tr069_sdk/axiros/axiros.py
hns_tr069_sdk/axiros/exceptions.py
hns_tr069_sdk-0.2.dist-info/LICENSE.txt
hns_tr069_sdk-0.2.dist-info/METADATA
hns_tr069_sdk-0.2.dist-info/WHEEL
hns_tr069_sdk-0.2.dist-info/top_level.txt
hns_tr069_sdk-0.2.dist-info/RECORD
