Metadata-Version: 2.1
Name: hns-tr069-sdk
Version: 0.2
Summary: TR069 server sdk
Home-page: https://gitlab.com/horsebridge/hns_tr069_sdk.git
Author: Nitin Sidhu
Author-email: nitin.sidhu23@gmail.com
License: MIT
Platform: UNKNOWN
Classifier: License :: OSI Approved :: MIT License
Classifier: Operating System :: OS Independent
Classifier: Programming Language :: Python :: 3.6
Classifier: Programming Language :: Python :: 3.7
Classifier: Programming Language :: Python :: 3.8
Requires-Python: ~=3.6
Requires-Dist: requests (<3,>=2)
